[{"group":"绑定","list":[{"title":"/bind","eg":"/bind <sessionToken>","desc":"绑定你的 sessionToken\neg: /bind abcdefghijklmnopqrstuvwxy"},{"title":"/unbind","eg":"/unbind","desc":"在 Bot 上删除储存的你的存档以及成绩记录，需要二次确认\neg: /unbind"},{"title":"/tk help","eg":"/tk help","desc":"获取 sessionToken 相关帮助文档"}]},{"group":"查询 & 统计","list":[{"title":"/update","eg":"/update","desc":"更新 Bot 端存储的成绩，/pgr 也可以自动更新\neg: /update"},{"title":"/pgr","eg":"/pgr [背景(可选)]","desc":"获取 B19 成绩图，在主题不为⌈使一颗心免于哀伤⌋时可以选择背景曲绘\neg1: /pgr    eg2: /pgr df"},{"title":"/info","eg":"/info [背景(可选)]","desc":"获取你的个人统计信息\neg1: /info    eg2: /info df"},{"title":"/score","eg":"/score <曲目>","desc":"获取单曲成绩\neg: /score df"},{"title":"/lvsco\n/scolv","eg":"/lvsco [定数] [难度]","desc":"获取指定范围内的成绩统计图\neg1: /lvsco 15+\neg2: /lvsco 14 IN HD\neg3: /lvsco 12-15 IN AT"},{"title":"/list","eg":"/list [定数] [难度] [评级]","desc":"列出所有匹配的成绩\neg: /list 15 F"},{"title":"/bN","eg":"/b<N>","desc":"B19 但是很长很长\neg: /b60"},{"title":"/bestN","eg":"/best <1-99>","desc":"获取文字版 B<N> 成绩，私聊获取完整版，建议私聊使用\neg: /best 19"},{"title":"/suggest","eg":"/suggest","desc":"获取推分（使游戏内显示数值+0.01）建议，私聊获取完整版，建议私聊使用\neg: /suggest"},{"title":"/data","eg":"/data","desc":"获取 data 数量\neg: /data"}]},{"group":"图鉴 & 功能","list":[{"title":"/song","eg":"/song <曲目>","desc":"查询曲目图鉴\neg: /song 996"},{"title":"/rand","eg":"/rand [定数] [难度]","desc":"随机谱面\neg1: /rand 13+\neg2: /rand 15-\neg3: /rand 14-16 AT"},{"title":"/search","eg":"/search [bpm N-N] [dif N-N] [cmb N-N]","desc":"查询符合条件的曲目，建议私聊使用\neg1: /search bpm 300\neg2: /search bpm 1-300 dif 15"}]},{"group":"娱乐 & 设定","list":[{"title":"/letter","eg":"/letter /第N个xx /ltr ans","desc":"开字母小游戏\neg1: /第一个996\neg2: /第一df"},{"title":"/guess","eg":"/guess (直接回答) /illans","desc":"猜曲绘，回答直接发曲目，识别后 Bot 会回复正确与否"},{"title":"/theme","eg":"/theme [0-2]","desc":"切换主题，作用于 pgr update list task\neg: /theme 1"},{"title":"/sign","eg":"/sign","desc":"签到打卡获取 Notes 和任务卡片\neg: /sign"},{"title":"/send","eg":"/send @ <N>","desc":"用于 Notes 转账，会从中扣除部分\neg: /send @xx 520"},{"title":"/task","eg":"/task","desc":"查看自己的任务\neg: /task"},{"title":"/retask","eg":"/retask","desc":"花费 20Notes 重置自己的任务，每日 /sgin 可视为一次 /retask ，每日第一次 reatask 免费\neg: /retask"}]}]